manga_dl4/MangaDL4.py
manga_dl4/__init__.py
manga_dl4/utility.py
manga_dl4-0.0.2.dist-info/LICENSE
manga_dl4-0.0.2.dist-info/METADATA
manga_dl4-0.0.2.dist-info/WHEEL
manga_dl4-0.0.2.dist-info/top_level.txt
manga_dl4-0.0.2.dist-info/RECORD
