Metadata-Version: 2.1
Name: manga-dl4
Version: 0.0.2
Summary: A Python Package To Download Manga From Arabic Site [3asq]
Home-page: https://github.com/dexter-90/manga-dl4
Author: Dexter
Author-email: 
Project-URL: Bug Tracker, https://github.com/mahesh-maximus/helloworld-pyp/issues
Classifier: Programming Language :: Python :: 3
Classifier: License :: OSI Approved :: MIT License
Requires-Python: >=3.6
License-File: LICENSE
Requires-Dist: requests
Requires-Dist: bs4
Requires-Dist: img2pdf
